xml_validator.pypy39-pp73-win_amd64.pyd
xml_validator-1.0.3.data/data/xml_validator.pyi
xml_validator-1.0.3.dist-info/licenses/LICENSE
xml_validator-1.0.3.dist-info/METADATA
xml_validator-1.0.3.dist-info/WHEEL
xml_validator-1.0.3.dist-info/top_level.txt
xml_validator-1.0.3.dist-info/RECORD
